orchestration/A2A_DESIGN.md
orchestration/AGENT_SESSION_CONFIG.md
orchestration/ATOMIC_LOCKING_README.md
orchestration/CLAUDE.md
orchestration/DYNAMIC_AGENT_DESIGN.md
orchestration/MONITORING_SAFETY.md
orchestration/ORCHESTRATION_QUICK_START.md
orchestration/README.md
orchestration/__init__.py
orchestration/a2a_agent_wrapper.py
orchestration/a2a_integration.py
orchestration/a2a_monitor.py
orchestration/agent_health_monitor.py
orchestration/agent_instructions.md
orchestration/agent_monitor.py
orchestration/agent_system.py
orchestration/cleanup_agents.sh
orchestration/cleanup_completed_agents.py
orchestration/cli_validation.py
orchestration/constants.py
orchestration/core.py
orchestration/dashboard.py
orchestration/debug_task_flow.py
orchestration/debug_worker.py
orchestration/live_mode.py
orchestration/message_broker.py
orchestration/monitor_agents.sh
orchestration/orchestrate_unified.py
orchestration/recovery_coordinator.py
orchestration/safe_agent_monitor.py
orchestration/start_monitor.sh
orchestration/start_system.sh
orchestration/stream_logs.sh
orchestration/task_dispatcher.py
orchestration/tmux-agent.conf
orchestration/config/a2a_config.yaml
jleechanorg_orchestration-0.1.34.dist-info/METADATA
jleechanorg_orchestration-0.1.34.dist-info/WHEEL
jleechanorg_orchestration-0.1.34.dist-info/entry_points.txt
jleechanorg_orchestration-0.1.34.dist-info/top_level.txt
jleechanorg_orchestration-0.1.34.dist-info/RECORD
