Metadata-Version: 2.4
Name: jleechanorg-orchestration
Version: 0.1.34
Summary: AI Orchestration - tmux-based interactive AI CLI wrapper and multi-agent orchestration system
Author-email: jleechan <jlee@jleechan.org>
License: MIT
Project-URL: Homepage, https://github.com/jleechanorg/worldarchitect.ai
Project-URL: Repository, https://github.com/jleechanorg/worldarchitect.ai
Project-URL: Issues, https://github.com/jleechanorg/worldarchitect.ai/issues
Project-URL: Documentation, https://github.com/jleechanorg/worldarchitect.ai/tree/main/orchestration
Keywords: ai,orchestration,tmux,claude,codex,cli,automation,agents,terminal,interactive
Classifier: Development Status :: 4 - Beta
Classifier: Intended Audience :: Developers
Classifier: Programming Language :: Python :: 3
Classifier: Programming Language :: Python :: 3.9
Classifier: Programming Language :: Python :: 3.10
Classifier: Programming Language :: Python :: 3.11
Classifier: Programming Language :: Python :: 3.12
Classifier: Topic :: Software Development :: Libraries :: Python Modules
Classifier: Topic :: System :: Shells
Classifier: Topic :: Terminals
Requires-Python: >=3.11
Provides-Extra: dev
Requires-Dist: pytest>=7.0.0; extra == "dev"
Requires-Dist: pytest-cov>=4.0.0; extra == "dev"
Requires-Dist: black>=22.0.0; extra == "dev"
Requires-Dist: ruff>=0.1.0; extra == "dev"
